<?xml version="1.0" encoding="utf-8"?>
<cardapio>
    <prato>
        <id>1</id>
        <nome>Spaghetti Carbonara</nome>
        <descricao>Prato tradicional italiano com ovos, queijo, pancetta e pimenta.</descricao>
        <preco>25.00</preco>
        <calorias>600</calorias>
        <tempoPreparo>30</tempoPreparo>
        <ingredientes>
            <ingrediente>
                <nome>Spaghetti</nome>
            </ingrediente>
            <ingrediente>
                <nome>Ovos</nome>
            </ingrediente>
            <ingrediente>
                <nome>Queijo</nome>
            </ingrediente>
            <ingrediente>
                <nome>Pancetta</nome>
            </ingrediente>
            <ingrediente>
                <nome>Pimenta</nome>
            </ingrediente>
        </ingredientes>
    </prato>

    <prato>
        <id>2</id>
        <nome>Chicken Caesar Salad</nome>
        <descricao>Alface romana fresca com frango grelhado, croutons, queijo Parmesan e molho Caesar.</descricao>
        <preco>20.00</preco>
        <calorias>450</calorias>
        <tempoPreparo>20</tempoPreparo>
        <ingredientes>
            <ingrediente>
                <nome>Alface Romana</nome>
            </ingrediente>
            <ingrediente>
                <nome>Frango Grelhado</nome>
            </ingrediente>
            <ingrediente>
                <nome>Croutons</nome>
            </ingrediente>
            <ingrediente>
                <nome>Queijo Parmesan</nome>
            </ingrediente>
            <ingrediente>
                <nome>Molho Caesar</nome>
            </ingrediente>
        </ingredientes>
    </prato>
</cardapio>